<TABLEMETADATA SCHEMANAME="EMPOWER" TABLENAME="PRICESTIPSETS"><RECORD-COUNT>10</RECORD-COUNT><DATATYPES><!-- 
						Legend
			
			(Java Database Connectivity (JDBC) is the communication standard used for all databases)
			
			DATATYPE
				[database column type] + [data length]
				
				Varies by original database and can be non-standard.
				
				Some databases embed a length in the type name, which can differ from actual reported data length
					e.g. for Oracle, TIMESTAMP(6)(11)
			
			JDBC-DATATYPE
				Standard column type, according to JDBC. Determines extraction handling.
		--><PRICESTIPSETS-TYPE><NAME>STIPNUM</NAME><COLNO>1</COLNO><DATATYPE>int</DATATYPE><JDBC-DATATYPE CODE="4">INTEGER</JDBC-DATATYPE></PRICESTIPSETS-TYPE><PRICESTIPSETS-TYPE><NAME>STIPDESC</NAME><COLNO>2</COLNO><DATATYPE>varchar(40)</DATATYPE><JDBC-DATATYPE CODE="12">VARCHAR</JDBC-DATATYPE></PRICESTIPSETS-TYPE><PRICESTIPSETS-TYPE><NAME>LASTMOD</NAME><COLNO>3</COLNO><DATATYPE>datetime</DATATYPE><JDBC-DATATYPE CODE="93">TIMESTAMP</JDBC-DATATYPE></PRICESTIPSETS-TYPE><PRICESTIPSETS-TYPE><NAME>BRANCHID</NAME><COLNO>4</COLNO><DATATYPE>int</DATATYPE><JDBC-DATATYPE CODE="4">INTEGER</JDBC-DATATYPE></PRICESTIPSETS-TYPE></DATATYPES><KEYS><PRICESTIPSETS-KEY><NAME>STIPNUM</NAME><CONSTRAINT_NAME>PK_PRICESTIPSETS</CONSTRAINT_NAME><TYPE>Primary Key</TYPE></PRICESTIPSETS-KEY></KEYS><INDEXES><PRICESTIPSETS-INDEX><NAME>PK_PRICESTIPSETS</NAME><COLUMN_NAME>STIPNUM</COLUMN_NAME></PRICESTIPSETS-INDEX></INDEXES></TABLEMETADATA>