<TABLEMETADATA SCHEMANAME="EMPOWER" TABLENAME="VM_USERSETTINGS"><RECORD-COUNT>0</RECORD-COUNT><DATATYPES><!-- 
						Legend
			
			(Java Database Connectivity (JDBC) is the communication standard used for all databases)
			
			DATATYPE
				[database column type] + [data length]
				
				Varies by original database and can be non-standard.
				
				Some databases embed a length in the type name, which can differ from actual reported data length
					e.g. for Oracle, TIMESTAMP(6)(11)
			
			JDBC-DATATYPE
				Standard column type, according to JDBC. Determines extraction handling.
		--><VM_USERSETTINGS-TYPE><NAME>USERID</NAME><COLNO>1</COLNO><DATATYPE>varchar(40)</DATATYPE><JDBC-DATATYPE CODE="12">VARCHAR</JDBC-DATATYPE></VM_USERSETTINGS-TYPE><VM_USERSETTINGS-TYPE><NAME>USERFILEPATH</NAME><COLNO>2</COLNO><DATATYPE>varchar(50)</DATATYPE><JDBC-DATATYPE CODE="12">VARCHAR</JDBC-DATATYPE></VM_USERSETTINGS-TYPE><VM_USERSETTINGS-TYPE><NAME>USERSCRIPTLIST</NAME><COLNO>3</COLNO><DATATYPE>image(2147483647)</DATATYPE><JDBC-DATATYPE CODE="2004">BLOB</JDBC-DATATYPE></VM_USERSETTINGS-TYPE><VM_USERSETTINGS-TYPE><NAME>OPTDELETE</NAME><COLNO>4</COLNO><DATATYPE>char(1)</DATATYPE><JDBC-DATATYPE CODE="1">CHAR</JDBC-DATATYPE></VM_USERSETTINGS-TYPE><VM_USERSETTINGS-TYPE><NAME>OPTPRMPT</NAME><COLNO>5</COLNO><DATATYPE>char(1)</DATATYPE><JDBC-DATATYPE CODE="1">CHAR</JDBC-DATATYPE></VM_USERSETTINGS-TYPE></DATATYPES><KEYS><VM_USERSETTINGS-KEY><NAME>USERID</NAME><CONSTRAINT_NAME>PK_VM_USERSETTINGS</CONSTRAINT_NAME><TYPE>Primary Key</TYPE></VM_USERSETTINGS-KEY></KEYS><INDEXES><VM_USERSETTINGS-INDEX><NAME>PK_VM_USERSETTINGS</NAME><COLUMN_NAME>USERID</COLUMN_NAME></VM_USERSETTINGS-INDEX></INDEXES></TABLEMETADATA>