<TABLEMETADATA SCHEMANAME="EMPOWER" TABLENAME="U_UPLOADOSIBOARDREJECTS"><RECORD-COUNT>0</RECORD-COUNT><DATATYPES><!-- 
						Legend
			
			(Java Database Connectivity (JDBC) is the communication standard used for all databases)
			
			DATATYPE
				[database column type] + [data length]
				
				Varies by original database and can be non-standard.
				
				Some databases embed a length in the type name, which can differ from actual reported data length
					e.g. for Oracle, TIMESTAMP(6)(11)
			
			JDBC-DATATYPE
				Standard column type, according to JDBC. Determines extraction handling.
		--><U_UPLOADOSIBOARDREJECTS-TYPE><NAME>ACCTNBR_001000</NAME><COLNO>1</COLNO><DATATYPE>varchar(20)</DATATYPE><JDBC-DATATYPE CODE="12">VARCHAR</JDBC-DATATYPE></U_UPLOADOSIBOARDREJECTS-TYPE><U_UPLOADOSIBOARDREJECTS-TYPE><NAME>IDX</NAME><COLNO>2</COLNO><DATATYPE>int</DATATYPE><JDBC-DATATYPE CODE="4">INTEGER</JDBC-DATATYPE></U_UPLOADOSIBOARDREJECTS-TYPE><U_UPLOADOSIBOARDREJECTS-TYPE><NAME>NETDIFF</NAME><COLNO>3</COLNO><DATATYPE>float</DATATYPE><JDBC-DATATYPE CODE="8">DOUBLE</JDBC-DATATYPE></U_UPLOADOSIBOARDREJECTS-TYPE><U_UPLOADOSIBOARDREJECTS-TYPE><NAME>REJECTREASON</NAME><COLNO>4</COLNO><DATATYPE>varchar(50)</DATATYPE><JDBC-DATATYPE CODE="12">VARCHAR</JDBC-DATATYPE></U_UPLOADOSIBOARDREJECTS-TYPE><U_UPLOADOSIBOARDREJECTS-TYPE><NAME>REJECTFIELD</NAME><COLNO>5</COLNO><DATATYPE>varchar(50)</DATATYPE><JDBC-DATATYPE CODE="12">VARCHAR</JDBC-DATATYPE></U_UPLOADOSIBOARDREJECTS-TYPE></DATATYPES><KEYS><U_UPLOADOSIBOARDREJECTS-KEY><NAME>AcctNbr_001000</NAME><CONSTRAINT_NAME>PK_Temp_UploadOSIBoardRejects</CONSTRAINT_NAME><TYPE>Primary Key</TYPE></U_UPLOADOSIBOARDREJECTS-KEY><U_UPLOADOSIBOARDREJECTS-KEY><NAME>IDX</NAME><CONSTRAINT_NAME>PK_Temp_UploadOSIBoardRejects</CONSTRAINT_NAME><TYPE>Primary Key</TYPE></U_UPLOADOSIBOARDREJECTS-KEY></KEYS><INDEXES><U_UPLOADOSIBOARDREJECTS-INDEX><NAME>PK_Temp_UploadOSIBoardRejects</NAME><COLUMN_NAME>AcctNbr_001000, IDX</COLUMN_NAME></U_UPLOADOSIBOARDREJECTS-INDEX></INDEXES></TABLEMETADATA>