<U_GL_PAYMENTS_CONT>
<U_GL_PAYMENTS_CONT-ROW><LNKEY>1234567891</LNKEY><IDX>1</IDX><MISC_FEE_DESC>MISC_FEE_DESC</MISC_FEE_DESC><MISC_FEE_AMT>1234.56</MISC_FEE_AMT><MISC_AMT_PAID>2345.67</MISC_AMT_PAID><MISC_CURR_BAL>3456.78</MISC_CURR_BAL><MISC_FEE_PAYEE>MISC_FEE_PAYEE</MISC_FEE_PAYEE><MISC_PD_CONFIRMED>1</MISC_PD_CONFIRMED><MISC_PD_CONFIRMED_DT>2018-01-02T00:00:00.000</MISC_PD_CONFIRMED_DT><MISC_INTERNAL_CHG>1</MISC_INTERNAL_CHG><MISC_COST_CENTER>MISC_COST_CENTER</MISC_COST_CENTER><MISC_FEE_GL_ACCOUNT>MISC_FEE_GL_ACCOUNT</MISC_FEE_GL_ACCOUNT><SENT_MISC_PMT>1</SENT_MISC_PMT></U_GL_PAYMENTS_CONT-ROW>
<U_GL_PAYMENTS_CONT-ROW><LNKEY>1234567891</LNKEY><IDX>2</IDX><MISC_FEE_DESC>MISC_FEE_DESC</MISC_FEE_DESC><MISC_FEE_AMT>1234.56</MISC_FEE_AMT><MISC_AMT_PAID>2345.67</MISC_AMT_PAID><MISC_CURR_BAL>3456.78</MISC_CURR_BAL><MISC_FEE_PAYEE>MISC_FEE_PAYEE</MISC_FEE_PAYEE><MISC_PD_CONFIRMED>1</MISC_PD_CONFIRMED><MISC_PD_CONFIRMED_DT>2018-01-02T00:00:00.000</MISC_PD_CONFIRMED_DT><MISC_INTERNAL_CHG>1</MISC_INTERNAL_CHG><MISC_COST_CENTER>MISC_COST_CENTER</MISC_COST_CENTER><MISC_FEE_GL_ACCOUNT>MISC_FEE_GL_ACCOUNT</MISC_FEE_GL_ACCOUNT><SENT_MISC_PMT>1</SENT_MISC_PMT></U_GL_PAYMENTS_CONT-ROW>
<U_GL_PAYMENTS_CONT-ROW><LNKEY>1234567891</LNKEY><IDX>3</IDX><MISC_FEE_DESC>MISC_FEE_DESC</MISC_FEE_DESC><MISC_FEE_AMT>1234.56</MISC_FEE_AMT><MISC_AMT_PAID>2345.67</MISC_AMT_PAID><MISC_CURR_BAL>3456.78</MISC_CURR_BAL><MISC_FEE_PAYEE>MISC_FEE_PAYEE</MISC_FEE_PAYEE><MISC_PD_CONFIRMED>1</MISC_PD_CONFIRMED><MISC_PD_CONFIRMED_DT>2018-01-02T00:00:00.000</MISC_PD_CONFIRMED_DT><MISC_INTERNAL_CHG>1</MISC_INTERNAL_CHG><MISC_COST_CENTER>MISC_COST_CENTER</MISC_COST_CENTER><MISC_FEE_GL_ACCOUNT>MISC_FEE_GL_ACCOUNT</MISC_FEE_GL_ACCOUNT><SENT_MISC_PMT>1</SENT_MISC_PMT></U_GL_PAYMENTS_CONT-ROW>
<U_GL_PAYMENTS_CONT-ROW><LNKEY>1234567892</LNKEY><IDX>1</IDX><MISC_FEE_DESC>MISC_FEE_DESC</MISC_FEE_DESC><MISC_FEE_AMT>1234.56</MISC_FEE_AMT><MISC_AMT_PAID>2345.67</MISC_AMT_PAID><MISC_CURR_BAL>3456.78</MISC_CURR_BAL><MISC_FEE_PAYEE>MISC_FEE_PAYEE</MISC_FEE_PAYEE><MISC_PD_CONFIRMED>1</MISC_PD_CONFIRMED><MISC_PD_CONFIRMED_DT>2018-01-02T00:00:00.000</MISC_PD_CONFIRMED_DT><MISC_INTERNAL_CHG>1</MISC_INTERNAL_CHG><MISC_COST_CENTER>MISC_COST_CENTER</MISC_COST_CENTER><MISC_FEE_GL_ACCOUNT>MISC_FEE_GL_ACCOUNT</MISC_FEE_GL_ACCOUNT><SENT_MISC_PMT>1</SENT_MISC_PMT></U_GL_PAYMENTS_CONT-ROW>
<U_GL_PAYMENTS_CONT-ROW><LNKEY>1234567893</LNKEY><IDX>1</IDX><MISC_FEE_DESC>MISC_FEE_DESC</MISC_FEE_DESC><MISC_FEE_AMT>1234.56</MISC_FEE_AMT><MISC_AMT_PAID>2345.67</MISC_AMT_PAID><MISC_CURR_BAL>3456.78</MISC_CURR_BAL><MISC_FEE_PAYEE>MISC_FEE_PAYEE</MISC_FEE_PAYEE><MISC_PD_CONFIRMED>1</MISC_PD_CONFIRMED><MISC_PD_CONFIRMED_DT>2018-01-02T00:00:00.000</MISC_PD_CONFIRMED_DT><MISC_INTERNAL_CHG>1</MISC_INTERNAL_CHG><MISC_COST_CENTER>MISC_COST_CENTER</MISC_COST_CENTER><MISC_FEE_GL_ACCOUNT>MISC_FEE_GL_ACCOUNT</MISC_FEE_GL_ACCOUNT><SENT_MISC_PMT>1</SENT_MISC_PMT></U_GL_PAYMENTS_CONT-ROW>
<U_GL_PAYMENTS_CONT-ROW><LNKEY>1234567894</LNKEY><IDX>1</IDX><MISC_FEE_DESC>MISC_FEE_DESC</MISC_FEE_DESC><MISC_FEE_AMT>1234.56</MISC_FEE_AMT><MISC_AMT_PAID>2345.67</MISC_AMT_PAID><MISC_CURR_BAL>3456.78</MISC_CURR_BAL><MISC_FEE_PAYEE>MISC_FEE_PAYEE</MISC_FEE_PAYEE><MISC_PD_CONFIRMED>1</MISC_PD_CONFIRMED><MISC_PD_CONFIRMED_DT>2018-01-02T00:00:00.000</MISC_PD_CONFIRMED_DT><MISC_INTERNAL_CHG>1</MISC_INTERNAL_CHG><MISC_COST_CENTER>MISC_COST_CENTER</MISC_COST_CENTER><MISC_FEE_GL_ACCOUNT>MISC_FEE_GL_ACCOUNT</MISC_FEE_GL_ACCOUNT><SENT_MISC_PMT>1</SENT_MISC_PMT></U_GL_PAYMENTS_CONT-ROW>
<U_GL_PAYMENTS_CONT-ROW><LNKEY>1234567895</LNKEY><IDX>1</IDX><MISC_FEE_DESC>MISC_FEE_DESC</MISC_FEE_DESC><MISC_FEE_AMT>1234.56</MISC_FEE_AMT><MISC_AMT_PAID>2345.67</MISC_AMT_PAID><MISC_CURR_BAL>3456.78</MISC_CURR_BAL><MISC_FEE_PAYEE>MISC_FEE_PAYEE</MISC_FEE_PAYEE><MISC_PD_CONFIRMED>1</MISC_PD_CONFIRMED><MISC_PD_CONFIRMED_DT>2018-01-02T00:00:00.000</MISC_PD_CONFIRMED_DT><MISC_INTERNAL_CHG>1</MISC_INTERNAL_CHG><MISC_COST_CENTER>MISC_COST_CENTER</MISC_COST_CENTER><MISC_FEE_GL_ACCOUNT>MISC_FEE_GL_ACCOUNT</MISC_FEE_GL_ACCOUNT><SENT_MISC_PMT>1</SENT_MISC_PMT></U_GL_PAYMENTS_CONT-ROW>
</U_GL_PAYMENTS_CONT>