<TABLEMETADATA SCHEMANAME="EMPOWER" TABLENAME="POST_CLOSING_STATUS"><RECORD-COUNT>0</RECORD-COUNT><DATATYPES><!-- 
						Legend
			
			(Java Database Connectivity (JDBC) is the communication standard used for all databases)
			
			DATATYPE
				[database column type] + [data length]
				
				Varies by original database and can be non-standard.
				
				Some databases embed a length in the type name, which can differ from actual reported data length
					e.g. for Oracle, TIMESTAMP(6)(11)
			
			JDBC-DATATYPE
				Standard column type, according to JDBC. Determines extraction handling.
		--><POST_CLOSING_STATUS-TYPE><NAME>LNKEY</NAME><COLNO>1</COLNO><DATATYPE>varchar(20)</DATATYPE><JDBC-DATATYPE CODE="12">VARCHAR</JDBC-DATATYPE></POST_CLOSING_STATUS-TYPE><POST_CLOSING_STATUS-TYPE><NAME>IDX</NAME><COLNO>2</COLNO><DATATYPE>int</DATATYPE><JDBC-DATATYPE CODE="4">INTEGER</JDBC-DATATYPE></POST_CLOSING_STATUS-TYPE><POST_CLOSING_STATUS-TYPE><NAME>VA_STATUS</NAME><COLNO>3</COLNO><DATATYPE>int</DATATYPE><JDBC-DATATYPE CODE="4">INTEGER</JDBC-DATATYPE></POST_CLOSING_STATUS-TYPE><POST_CLOSING_STATUS-TYPE><NAME>UW_COND_STATUS</NAME><COLNO>4</COLNO><DATATYPE>int</DATATYPE><JDBC-DATATYPE CODE="4">INTEGER</JDBC-DATATYPE></POST_CLOSING_STATUS-TYPE><POST_CLOSING_STATUS-TYPE><NAME>SERVICING_STATUS</NAME><COLNO>5</COLNO><DATATYPE>int</DATATYPE><JDBC-DATATYPE CODE="4">INTEGER</JDBC-DATATYPE></POST_CLOSING_STATUS-TYPE><POST_CLOSING_STATUS-TYPE><NAME>NOTE_STATUS</NAME><COLNO>6</COLNO><DATATYPE>int</DATATYPE><JDBC-DATATYPE CODE="4">INTEGER</JDBC-DATATYPE></POST_CLOSING_STATUS-TYPE><POST_CLOSING_STATUS-TYPE><NAME>MORTGAGE_STATUS</NAME><COLNO>7</COLNO><DATATYPE>int</DATATYPE><JDBC-DATATYPE CODE="4">INTEGER</JDBC-DATATYPE></POST_CLOSING_STATUS-TYPE><POST_CLOSING_STATUS-TYPE><NAME>TITLE_STATUS</NAME><COLNO>8</COLNO><DATATYPE>int</DATATYPE><JDBC-DATATYPE CODE="4">INTEGER</JDBC-DATATYPE></POST_CLOSING_STATUS-TYPE><POST_CLOSING_STATUS-TYPE><NAME>HUD_STATUS</NAME><COLNO>9</COLNO><DATATYPE>int</DATATYPE><JDBC-DATATYPE CODE="4">INTEGER</JDBC-DATATYPE></POST_CLOSING_STATUS-TYPE><POST_CLOSING_STATUS-TYPE><NAME>FHA_STATUS</NAME><COLNO>10</COLNO><DATATYPE>int</DATATYPE><JDBC-DATATYPE CODE="4">INTEGER</JDBC-DATATYPE></POST_CLOSING_STATUS-TYPE><POST_CLOSING_STATUS-TYPE><NAME>CLOSING_STATUS</NAME><COLNO>11</COLNO><DATATYPE>int</DATATYPE><JDBC-DATATYPE CODE="4">INTEGER</JDBC-DATATYPE></POST_CLOSING_STATUS-TYPE></DATATYPES><KEYS><POST_CLOSING_STATUS-KEY><NAME>LNKEY</NAME><CONSTRAINT_NAME>PK_POST_CLOSING_STATUS</CONSTRAINT_NAME><TYPE>Primary Key</TYPE></POST_CLOSING_STATUS-KEY><POST_CLOSING_STATUS-KEY><NAME>IDX</NAME><CONSTRAINT_NAME>PK_POST_CLOSING_STATUS</CONSTRAINT_NAME><TYPE>Primary Key</TYPE></POST_CLOSING_STATUS-KEY></KEYS><INDEXES><POST_CLOSING_STATUS-INDEX><NAME>PK_POST_CLOSING_STATUS</NAME><COLUMN_NAME>LNKEY, IDX</COLUMN_NAME></POST_CLOSING_STATUS-INDEX></INDEXES></TABLEMETADATA>